[
  {
    "key": "ctrl+n",
    "command": "workbench.action.toggleSidebarVisibility"
  },
  {
    "key": "ctrl+p",
    "command": "workbench.action.quickOpen"
  },
  {
    "key": "ctrl+p",
    "command": "workbench.action.quickOpenNavigateNextInFilePicker",
    "when": "inFilesPicker && inQuickOpen"
  },
  {
    "key": "ctrl+k",
    "command": "selectPrevSuggestion",
    "when": "suggestWidgetMultipleSuggestions && suggestWidgetVisible && textInputFocus"
  },
  {
    "key": "ctrl+k",
    "command": "workbench.action.quickOpenSelectPrevious",
    "when": "inQuickOpen"
  },
  {
    "key": "ctrl+k",
    "command": "list.focusUp",
    "when": "listFocus && !inputFocus"
  },
  {
    "key": "ctrl+j",
    "command": "selectNextSuggestion",
    "when": "suggestWidgetMultipleSuggestions && suggestWidgetVisible && textInputFocus"
  },
  {
    "key": "ctrl+j",
    "command": "workbench.action.quickOpenSelectNext",
    "when": "inQuickOpen"
  },
  {
    "key": "ctrl+j",
    "command": "list.focusDown",
    "when": "listFocus && !inputFocus"
  },
  {
    "key": "ctrl+h",
    "command": "workbench.action.navigateLeft",
    "when": "!suggestWidgetMultipleSuggestions && !suggestWidgetVisible && !inQuickOpen"
  },
  {
    "key": "ctrl+l",
    "command": "workbench.action.navigateRight",
    "when": "!suggestWidgetMultipleSuggestions && !suggestWidgetVisible && !inQuickOpen"
  },
  {
    "key": "ctrl+k",
    "command": "workbench.action.navigateUp",
    "when": "!suggestWidgetMultipleSuggestions && !suggestWidgetVisible && !inQuickOpen"
  },
  {
    "key": "ctrl+j",
    "command": "workbench.action.navigateDown",
    "when": "!suggestWidgetMultipleSuggestions && !suggestWidgetVisible && !inQuickOpen"
  },
  {
    "key": "enter",
    "command": "list.select",
    "when": "listFocus && !inputFocus"
  },
  {
    "key": "m m",
    "command": "renameFile",
    "when": "explorerViewletVisible && filesExplorerFocus && !explorerResourceIsRoot && !inputFocus"
  },
  {
    "key": "enter",
    "command": "-renameFile",
    "when": "explorerViewletVisible && filesExplorerFocus && !explorerResourceIsRoot && !inputFocus"
  },
  {
    "key": "m a",
    "command": "explorer.newFile",
    "when": "explorerViewletVisible && filesExplorerFocus && !explorerResourceIsRoot && !inputFocus"
  },
  {
    "key": "m d",
    "command": "deleteFile",
    "when": "explorerViewletVisible && filesExplorerFocus && !explorerResourceIsRoot && !inputFocus"
  },
  {
    "key": "alt+cmd+backspace",
    "command": "-deleteFile",
    "when": "explorerViewletVisible && filesExplorerFocus && !explorerResourceIsRoot && !inputFocus"
  },
  {
    "key": "m f",
    "command": "explorer.newFolder",
    "when": "explorerViewletVisible && filesExplorerFocus && !explorerResourceIsRoot && !inputFocus"
  },
  {
    "key": "ctrl+[",
    "command": "workbench.action.closeQuickOpen",
    "when": "inQuickOpen"
  },
  {
    "key": "ctrl+s",
    "command": "explorer.openToSide",
    "when": "explorerViewletFocus && explorerViewletVisible && !inputFocus"
  },
  {
    "key": "ctrl+s",
    "command": "openReferenceToSide",
    "when": "referenceSearchTreeFocused && referenceSearchVisible"
  },
  {
    "key": "ctrl+s",
    "command": "problems.action.openToSide",
    "when": "problemFocus"
  },
  {
    "key": "ctrl+s",
    "command": "search.action.openResultToSide",
    "when": "fileMatchOrMatchFocus && searchViewletVisible"
  },
  {
    "key": "ctrl+j",
    "command": "search.focus.nextInputBox",
    "when": "inputBoxFocus && searchViewletVisible"
  },
  {
    "key": "cmd+down",
    "command": "-search.focus.nextInputBox",
    "when": "inputBoxFocus && searchViewletVisible"
  },
  {
    "key": "ctrl+k",
    "command": "search.focus.previousInputBox",
    "when": "inputBoxFocus && searchViewletVisible && !searchInputBoxFocus"
  },
  {
    "key": "cmd+up",
    "command": "-search.focus.previousInputBox",
    "when": "inputBoxFocus && searchViewletVisible && !searchInputBoxFocus"
  },
  {
    "key": "alt+enter",
    "command": "editor.action.quickFix",
    "when": "editorHasCodeActionsProvider && editorTextFocus && !editorReadonly"
  }
]
